Workbook
Name Information: 'Executive Summary'!$B$14:$C$18

Sheet Executive Summary
B7: Project Scope
B8: The source guideline requires calculation of asset price, annual Straight-Line depreciation, depreciation percentage, total depreciation, ending book value and balance; the Diminishing Balance rate and a 10-year schedule; advanced questions; and a presentation with visual graphs.
B13: Key Information | E13: Key Output
B14: Asset Cost | C14: 450000 | E14: Straight-Line Annual Depreciation
B15: Additional Asset Cost | C15: 50000 | E15: Straight-Line Rate
B16: Asset Price / Depreciable Cost | C16: =C14+C15 -> 500000 | E16: Diminishing Balance Rate
B17: Scrap Value | C17: 50000 | E17: DB Year 2 Depreciation
B18: Useful Life (Years) | C18: 10 | E18: DB Year 4 Ending Book Value
B20: Conclusion
B21: Straight-Line produces a constant annual charge and reaches the scrap value only because the depreciable amount is evenly allocated. Diminishing Balance produces higher depreciation in earlier years and progressively lower charges, matching assets that lose value or become obsolete faster.

Sheet Depreciation Calculator
A1: Depreciation Calculator
A3: Straight Line Method
A4: Metric | B4: Formula / Value | C4: Formula | D4: Interpretation | F4: Year | G4: Beginning Book Value | H4: Year on Year Depreciation Amount | I4: Ending Book Value
A5: Asset Cost | B5: 450000 | D5: Initial cost of the asset. | F5: 1 | G5: =$B$7 -> 500000 | H5: =$B$10 -> 45000 | I5: =G5-H5 -> 455000
A6: Additonal Asset Cost | B6: 50000 | D6: Transportation, installation, setup and other acquisition costs. | F6: 2 | G6: =I5 -> 455000 | H6: =$B$10 -> 45000 | I6: =G6-H6 -> 410000
A7: Asset Price | B7: =SUM(B5:B6) -> 500000 | D7: Total asset cost including additional asset costs. | F7: 3 | G7: =I6 -> 410000 | H7: =$B$10 -> 45000 | I7: =G7-H7 -> 365000
A8: Scrap Value | B8: 50000 | D8: Estimated residual/salvage value at the end of useful life. | F8: 4 | G8: =I7 -> 365000 | H8: =$B$10 -> 45000 | I8: =G8-H8 -> 320000
A9: Estimated Life Span (Years) | B9: 10 | D9: Expected number of years over which the asset is depreciated. | F9: 5 | G9: =I8 -> 320000 | H9: =$B$10 -> 45000 | I9: =G9-H9 -> 275000
A10: Depreciation / Year as per Straight Line Method | B10: =(B7-B8)/B9 -> 45000 | C10: (Asset Price − Scrap Value) / Life | D10: Equal depreciation expense each year. | F10: 6 | G10: =I9 -> 275000 | H10: =$B$10 -> 45000 | I10: =G10-H10 -> 230000
A11: Depreciation Percentage | B11: =B10/B7 -> 0.09 | C11: Annual SL Depreciation / Asset Price | D11: Annual depreciation expressed as a percentage of asset price. | F11: 7 | G11: =I10 -> 230000 | H11: =$B$10 -> 45000 | I11: =G11-H11 -> 185000
A12: Total Depreciation For Its Life Span | B12: =B9*B10 -> 450000 | F12: 8 | G12: =I11 -> 185000 | H12: =$B$10 -> 45000 | I12: =G12-H12 -> 140000
A13: Depreciated Book Value After Its Life Span | B13: =B7-B12 -> 50000 | F13: 9 | G13: =I12 -> 140000 | H13: =$B$10 -> 45000 | I13: =G13-H13 -> 95000
A14: Balance Amount | B14: =B8-B13 -> 0 | D14: Balance amount should be 0 | F14: 10 | G14: =I13 -> 95000 | H14: =$B$10 -> 45000 | I14: =G14-H14 -> 50000
A16: Diminishing Balance Method
A17: Metric | B17: Formula / Value | C17: Formula | D17: Interpretation | F17: Year | G17: Beginning Book Value | H17: Year on Year Depreciation Amount | I17: Ending Book Value
A18: Asset Cost | B18: 450000 | F18: 1 | G18: =$B$20 -> 500000 | H18: =G18*$B$23 -> 102835.88 | I18: =IF(F18=$B$22,$B$21,G18-H18) -> 397164.12
A19: Additonal Asset Cost | B19: 50000 | F19: 2 | G19: =I18 -> 397164.12 | H19: =G19*$B$23 -> 81685.445 | I19: =IF(F19=$B$22,$B$21,G19-H19) -> 315478.67
A20: Asset Price | B20: =SUM(B18:B19) -> 500000 | D20: In case of diminishing depreciation scrap value cannot be zero | F20: 3 | G20: =I19 -> 315478.67 | H20: =G20*$B$23 -> 64885.055 | I20: =IF(F20=$B$22,$B$21,G20-H20) -> 250593.62
A21: Scrap Value | B21: 50000 | F21: 4 | G21: =I20 -> 250593.62 | H21: =G21*$B$23 -> 51540.032 | I21: =IF(F21=$B$22,$B$21,G21-H21) -> 199053.59
A22: Estimated Life Span (Years) | B22: 10 | F22: 5 | G22: =I21 -> 199053.59 | H22: =G22*$B$23 -> 40939.702 | I22: =IF(F22=$B$22,$B$21,G22-H22) -> 158113.88
A23: Rate of Depreciation as per Diminishing Balance Method | B23: =1-(B21/B20)^(1/B22) -> 0.20567177 | C23: 1 − (Scrap Value / Asset Price)^(1 / Life) | D23: Rate calibrated so the asset approaches the scrap value over the stated life. | F23: 6 | G23: =I22 -> 158113.88 | H23: =G23*$B$23 -> 32519.561 | I23: =IF(F23=$B$22,$B$21,G23-H23) -> 125594.32
A24: Depreciation | B24: =B20*B23 -> 102835.88 | C24: Beginning Book Value × DB Rate | D24: Higher expense earlier; lower expense later. | F24: 7 | G24: =I23 -> 125594.32 | H24: =G24*$B$23 -> 25831.206 | I24: =IF(F24=$B$22,$B$21,G24-H24) -> 99763.116
A25: Ending Book Value | B25: =B20-B24 -> 397164.12 | C25: Beginning Book Value − DB Depreciation | D25: Closing carrying amount for each year. | F25: 8 | G25: =I24 -> 99763.116 | H25: =G25*$B$23 -> 20518.456 | I25: =IF(F25=$B$22,$B$21,G25-H25) -> 79244.66
F26: 9 | G26: =I25 -> 79244.66 | H26: =G26*$B$23 -> 16298.389 | I26: =IF(F26=$B$22,$B$21,G26-H26) -> 62946.271
F27: 10 | G27: =I26 -> 62946.271 | H27: =G27*$B$23 -> 12946.271 | I27: =IF(F27=$B$22,$B$21,G27-H27) -> 50000

Sheet Advanced Answers
A1: Sl. No. | B1: Question | C1: Answer
A2: 1 | B2: Calculate annual depreciation using Straight-Line. | C2: ='Depreciation Calculator'!B10 -> 45000
A3: 2 | B3: Calculate total depreciation for the full life using Straight-Line. | C3: ='Depreciation Calculator'!B12 -> 450000
A4: 3 | B4: Find depreciated book value after life using Straight-Line. | C4: ='Depreciation Calculator'!B13 -> 50000
A5: 4 | B5: Calculate DB rate per year. | C5: ='Depreciation Calculator'!B23 -> 0.20567177
A6: 5 | B6: Calculate depreciation in Year 2 using DB. | C6: ='Depreciation Calculator'!H19 -> 81685.445
A7: 6 | B7: Find book value in Year 4 using DB. | C7: ='Depreciation Calculator'!I21 -> 199053.59
A8: 7 | B8: Calculate total depreciation over full life using DB. | C8: ='Depreciation Calculator'!B20-'Depreciation Calculator'!I27 -> 450000
A9: 8 | B9: Find book value after life using DB. | C9: ='Depreciation Calculator'!I27 -> 50000
A10: 9 | B10: Compare total depreciation under both methods. | C10: =SUM('Depreciation Calculator'!H5:H14)-SUM('Depreciation Calculator'!H18:H27) -> 0

Sheet Dashboard
A2: Year | B2: Straight-Line Depreciation | C2: Diminishing Balance Depreciation | D2: SL Ending BV | E2: DB Ending BV
A3: 1 | B3: ='Depreciation Calculator'!H5 -> 45000 | C3: ='Depreciation Calculator'!H18 -> 102835.88 | D3: ='Depreciation Calculator'!I5 -> 455000 | E3: ='Depreciation Calculator'!I18 -> 397164.12
A4: 2 | B4: ='Depreciation Calculator'!H6 -> 45000 | C4: ='Depreciation Calculator'!H19 -> 81685.445 | D4: ='Depreciation Calculator'!I6 -> 410000 | E4: ='Depreciation Calculator'!I19 -> 315478.67
A5: 3 | B5: ='Depreciation Calculator'!H7 -> 45000 | C5: ='Depreciation Calculator'!H20 -> 64885.055 | D5: ='Depreciation Calculator'!I7 -> 365000 | E5: ='Depreciation Calculator'!I20 -> 250593.62
A6: 4 | B6: ='Depreciation Calculator'!H8 -> 45000 | C6: ='Depreciation Calculator'!H21 -> 51540.032 | D6: ='Depreciation Calculator'!I8 -> 320000 | E6: ='Depreciation Calculator'!I21 -> 199053.59
A7: 5 | B7: ='Depreciation Calculator'!H9 -> 45000 | C7: ='Depreciation Calculator'!H22 -> 40939.702 | D7: ='Depreciation Calculator'!I9 -> 275000 | E7: ='Depreciation Calculator'!I22 -> 158113.88
A8: 6 | B8: ='Depreciation Calculator'!H10 -> 45000 | C8: ='Depreciation Calculator'!H23 -> 32519.561 | D8: ='Depreciation Calculator'!I10 -> 230000 | E8: ='Depreciation Calculator'!I23 -> 125594.32
A9: 7 | B9: ='Depreciation Calculator'!H11 -> 45000 | C9: ='Depreciation Calculator'!H24 -> 25831.206 | D9: ='Depreciation Calculator'!I11 -> 185000 | E9: ='Depreciation Calculator'!I24 -> 99763.116
A10: 8 | B10: ='Depreciation Calculator'!H12 -> 45000 | C10: ='Depreciation Calculator'!H25 -> 20518.456 | D10: ='Depreciation Calculator'!I12 -> 140000 | E10: ='Depreciation Calculator'!I25 -> 79244.66
A11: 9 | B11: ='Depreciation Calculator'!H13 -> 45000 | C11: ='Depreciation Calculator'!H26 -> 16298.389 | D11: ='Depreciation Calculator'!I13 -> 95000 | E11: ='Depreciation Calculator'!I26 -> 62946.271
A12: 10 | B12: ='Depreciation Calculator'!H14 -> 45000 | C12: ='Depreciation Calculator'!H27 -> 12946.271 | D12: ='Depreciation Calculator'!I14 -> 50000 | E12: ='Depreciation Calculator'!I27 -> 50000
A15: Insight
A16: Straight-Line depreciation remains constant at 45,000 per year. Diminishing Balance starts at about 102,835.88 in Year 1 and declines each year. Both methods allocate the same total depreciable amount of 450,000 and reach the 50,000 scrap value when modeled over the full 10-year life.
